django_json_schema_editor/__init__.py
django_json_schema_editor/fields.py
django_json_schema_editor/forms.py
django_json_schema_editor/plugins.py
django_json_schema_editor/static/django_json_schema_editor/django_theme.css
django_json_schema_editor/static/django_json_schema_editor/django_theme.js
django_json_schema_editor/static/django_json_schema_editor/foreign_key.js
django_json_schema_editor/static/django_json_schema_editor/language_de.js
django_json_schema_editor/static/django_json_schema_editor/prose_editor.js
django_json_schema_editor/static/django_json_schema_editor/widget.js
django_json_schema_editor/static/django_json_schema_editor/vendor/jsoneditor.js
django_json_schema_editor/static/django_json_schema_editor/vendor/material-icons.css
django_json_schema_editor/static/django_json_schema_editor/vendor/material-icons.woff2
django_json_schema_editor/templates/django_json_schema_editor/widget.html
django_json_schema_editor-0.12.1.dist-info/METADATA
django_json_schema_editor-0.12.1.dist-info/WHEEL
django_json_schema_editor-0.12.1.dist-info/RECORD
