Metadata-Version: 2.4
Name: django-json-schema-editor
Version: 0.12.1
Summary: Django widget for using @json-editor/json-editor in the admin
Project-URL: Documentation, https://github.com/matthiask/django-json-schema-editor#readme
Project-URL: Issues, https://github.com/matthiask/django-json-schema-editor/issues
Project-URL: Source, https://github.com/matthiask/django-json-schema-editor/
Author-email: Matthias Kestenholz <mk@feinheit.ch>, Fabian Germann <fg@feinheit.ch>
License: MIT
Classifier: Development Status :: 4 - Beta
Classifier: Programming Language :: Python
Classifier: Programming Language :: Python :: 3 :: Only
Classifier: Programming Language :: Python :: 3.9
Classifier: Programming Language :: Python :: 3.10
Classifier: Programming Language :: Python :: 3.11
Classifier: Programming Language :: Python :: 3.12
Classifier: Programming Language :: Python :: 3.13
Classifier: Programming Language :: Python :: 3.14
Requires-Python: >=3.9
Requires-Dist: django-js-asset>=3
Requires-Dist: fastjsonschema>=2.19
Requires-Dist: jmespath
Provides-Extra: prose
Requires-Dist: django-prose-editor>=0.11b3; extra == 'prose'
Provides-Extra: tests
Requires-Dist: asgiref; extra == 'tests'
Requires-Dist: coverage; extra == 'tests'
Requires-Dist: django-content-editor; extra == 'tests'
Requires-Dist: pytest; extra == 'tests'
Requires-Dist: pytest-asyncio; extra == 'tests'
Requires-Dist: pytest-cov; extra == 'tests'
Requires-Dist: pytest-django; extra == 'tests'
Requires-Dist: pytest-playwright; extra == 'tests'
